django_weblog-0.2.0.dist-info/DESCRIPTION.rst
django_weblog-0.2.0.dist-info/METADATA
django_weblog-0.2.0.dist-info/RECORD
django_weblog-0.2.0.dist-info/WHEEL
django_weblog-0.2.0.dist-info/pydist.json
django_weblog-0.2.0.dist-info/top_level.txt
weblog/__init__.py
weblog/admin.py
weblog/feeds.py
weblog/fields.py
weblog/managers.py
weblog/models.py
weblog/search_indexes.py
weblog/tests.py
weblog/urls.py
weblog/views.py
weblog/fixtures/weblog.json
weblog/templates/comments/_comment_form.html
weblog/templates/comments/comment_notification_email.txt
weblog/templates/comments/preview.html
weblog/templates/search/indexes/weblog/post_text.txt
weblog/templates/weblog/_post_body.html
weblog/templates/weblog/_widget_archive.html
weblog/templates/weblog/_widget_categories.html
weblog/templates/weblog/base.html
weblog/templates/weblog/category_detail.html
weblog/templates/weblog/category_list.html
weblog/templates/weblog/post_archive.html
weblog/templates/weblog/post_archive_day.html
weblog/templates/weblog/post_archive_month.html
weblog/templates/weblog/post_archive_year.html
weblog/templates/weblog/post_detail.html
weblog/templates/weblog/post_list.html
weblog/templates/weblog/search.html
weblog/templatetags/__init__.py
weblog/templatetags/recurse.py
weblog/templatetags/weblog_extras.py
