Metadata-Version: 2.0
Name: django-weblog
Version: 0.2.0
Summary: A Django weblog app with hierarchic categories.
Home-page: https://bitbucket.org/ssc/django-weblog
Author: Stefan Scherfke
Author-email: stefan at sofa-rockers.org
License: MIT
Platform: UNKNOWN
Classifier: Development Status :: 4 - Beta
Classifier: Intended Audience :: Developers
Classifier: Natural Language :: English
Classifier: License :: OSI Approved :: MIT License
Classifier: Operating System :: OS Independent
Classifier: Environment :: Web Environment
Classifier: Framework :: Django
Classifier: Programming Language :: Python
Classifier: Programming Language :: Python :: 2
Classifier: Programming Language :: Python :: 2.7
Classifier: Topic :: Software Development :: Libraries :: Python Modules
Classifier: Topic :: Utilities
Requires-Dist: Django (>=1.4)
Requires-Dist: django-haystack (>=2.1)
